Topsis-Sidak-102003649/__init__.py
Topsis-Sidak-102003649/__main__.py
topsisfile/__init__.py
topsisfile/__main__.py
Topsis_Sidak_102003649-1.0.3.dist-info/LICENSE
Topsis_Sidak_102003649-1.0.3.dist-info/METADATA
Topsis_Sidak_102003649-1.0.3.dist-info/WHEEL
Topsis_Sidak_102003649-1.0.3.dist-info/entry_points.txt
Topsis_Sidak_102003649-1.0.3.dist-info/top_level.txt
Topsis_Sidak_102003649-1.0.3.dist-info/RECORD
