Metadata-Version: 2.1
Name: Topsis-Sidak-102003649
Version: 1.0.3
Summary: Compute Topsis Scores/Ranks of a given csv file
Home-page: https://https://github.com/sidak2609/topsis
Author: Sidak Khotra
Author-email: sidakkhotra@gmail.com
License: MIT
Classifier: License :: OSI Approved :: MIT License
Classifier: Programming Language :: Python :: 3.6
Classifier: Programming Language :: Python :: 3.7
Classifier: Programming Language :: Python :: 3.8
License-File: LICENSE
Requires-Dist: Topsis-Sidak-102003649
